jaxsim/__init__.py
jaxsim/_version.py
jaxsim/exceptions.py
jaxsim/logging.py
jaxsim/typing.py
jaxsim/api/__init__.py
jaxsim/api/actuation_model.py
jaxsim/api/com.py
jaxsim/api/common.py
jaxsim/api/contact.py
jaxsim/api/data.py
jaxsim/api/frame.py
jaxsim/api/integrators.py
jaxsim/api/joint.py
jaxsim/api/kin_dyn_parameters.py
jaxsim/api/link.py
jaxsim/api/model.py
jaxsim/api/ode.py
jaxsim/api/references.py
jaxsim/math/__init__.py
jaxsim/math/adjoint.py
jaxsim/math/cross.py
jaxsim/math/inertia.py
jaxsim/math/joint_model.py
jaxsim/math/quaternion.py
jaxsim/math/rotation.py
jaxsim/math/skew.py
jaxsim/math/transform.py
jaxsim/math/utils.py
jaxsim/mujoco/__init__.py
jaxsim/mujoco/__main__.py
jaxsim/mujoco/loaders.py
jaxsim/mujoco/model.py
jaxsim/mujoco/utils.py
jaxsim/mujoco/visualizer.py
jaxsim/parsers/__init__.py
jaxsim/parsers/kinematic_graph.py
jaxsim/parsers/descriptions/__init__.py
jaxsim/parsers/descriptions/collision.py
jaxsim/parsers/descriptions/joint.py
jaxsim/parsers/descriptions/link.py
jaxsim/parsers/descriptions/model.py
jaxsim/parsers/rod/__init__.py
jaxsim/parsers/rod/meshes.py
jaxsim/parsers/rod/parser.py
jaxsim/parsers/rod/utils.py
jaxsim/rbda/__init__.py
jaxsim/rbda/aba.py
jaxsim/rbda/collidable_points.py
jaxsim/rbda/crba.py
jaxsim/rbda/forward_kinematics.py
jaxsim/rbda/jacobian.py
jaxsim/rbda/kinematic_constraints.py
jaxsim/rbda/rnea.py
jaxsim/rbda/utils.py
jaxsim/rbda/actuation/__init__.py
jaxsim/rbda/actuation/common.py
jaxsim/rbda/contacts/__init__.py
jaxsim/rbda/contacts/common.py
jaxsim/rbda/contacts/relaxed_rigid.py
jaxsim/rbda/contacts/rigid.py
jaxsim/rbda/contacts/soft.py
jaxsim/terrain/__init__.py
jaxsim/terrain/terrain.py
jaxsim/utils/__init__.py
jaxsim/utils/jaxsim_dataclass.py
jaxsim/utils/tracing.py
jaxsim/utils/wrappers.py
jaxsim-0.8.0.dist-info/licenses/LICENSE
jaxsim-0.8.0.dist-info/METADATA
jaxsim-0.8.0.dist-info/WHEEL
jaxsim-0.8.0.dist-info/top_level.txt
jaxsim-0.8.0.dist-info/RECORD
