Metadata-Version: 2.4
Name: jaxsim
Version: 0.8.0
Summary: A differentiable physics engine and multibody dynamics library for control and robot learning.
Author-email: Diego Ferigo <dgferigo@gmail.com>, Filippo Luca Ferretti <filippoluca.ferretti@outlook.com>
Maintainer-email: Filippo Luca Ferretti <filippo.ferretti@iit.it>, Alessandro Croci <alessandro.croci@iit.it>
License-Expression: BSD-3-Clause
Project-URL: Changelog, https://github.com/ami-iit/jaxsim/releases
Project-URL: Documentation, https://jaxsim.readthedocs.io
Project-URL: Source, https://github.com/ami-iit/jaxsim
Project-URL: Tracker, https://github.com/ami-iit/jaxsim/issues
Keywords: physics,physics engine,jax,rigid body dynamics,featherstone,reinforcement learning,robot,robotics,sdf,urdf
Classifier: Development Status :: 4 - Beta
Classifier: Framework :: Robot Framework
Classifier: Intended Audience :: Developers
Classifier: Intended Audience :: Science/Research
Classifier: Operating System :: POSIX :: Linux
Classifier: Operating System :: MacOS
Classifier: Operating System :: Microsoft
Classifier: Programming Language :: Python :: 3 :: Only
Classifier: Programming Language :: Python :: 3.10
Classifier: Programming Language :: Python :: 3.11
Classifier: Programming Language :: Python :: 3.12
Classifier: Programming Language :: Python :: 3.13
Classifier: Programming Language :: Python :: Implementation :: CPython
Classifier: Topic :: Games/Entertainment :: Simulation
Classifier: Topic :: Scientific/Engineering :: Artificial Intelligence
Classifier: Topic :: Scientific/Engineering :: Physics
Classifier: Topic :: Software Development
Requires-Python: >=3.10
License-File: LICENSE
Requires-Dist: coloredlogs
Requires-Dist: jax>=0.4.34
Requires-Dist: jaxlib>=0.4.34
Requires-Dist: jaxlie>=1.3.0
Requires-Dist: jax_dataclasses>=1.4.0
Requires-Dist: pptree
Requires-Dist: optax>=0.2.3
Requires-Dist: qpax
Requires-Dist: rod>=0.3.3
Requires-Dist: typing_extensions; python_version < "3.12"
Requires-Dist: trimesh
Provides-Extra: style
Requires-Dist: black[jupyter]~=24.0; extra == "style"
Requires-Dist: isort; extra == "style"
Requires-Dist: pre-commit; extra == "style"
Provides-Extra: testing
Requires-Dist: idyntree>=12.2.1; extra == "testing"
Requires-Dist: pytest>=6.0; extra == "testing"
Requires-Dist: pytest-benchmark; extra == "testing"
Requires-Dist: pytest-icdiff; extra == "testing"
Requires-Dist: robot-descriptions>=1.16.0; extra == "testing"
Requires-Dist: icub-models; extra == "testing"
Provides-Extra: viz
Requires-Dist: lxml; extra == "viz"
Requires-Dist: mediapy; extra == "viz"
Requires-Dist: mujoco>=3.0.0; extra == "viz"
Requires-Dist: scipy>=1.14.0; extra == "viz"
Provides-Extra: all
Requires-Dist: jaxsim[style,testing,viz]; extra == "all"
Dynamic: license-file
